[
  {
    "id": "50_2024_TT-BGTVT_chunk_1",
    "text": "Thông Tư\n50/2024/TT-BGTVT\nBAN HÀNH QUY CHUẨN KỸ THUẬT QUỐC GIA VỀ CƠ SỞ VẬT CHẤT KỸ THUẬT VÀ VỊ TRÍ CƠ SỞ ĐĂNG KIỂM XE CƠ GIỚI, CƠ SỞ KIỂM ĐỊNH KHÍ THẢI XE MÔ TÔ, XE GẮN MÁY VÀ QUY CHUẨN KỸ THUẬT QUỐC GIA VỀ CƠ SỞ BẢO HÀNH, BẢO DƯỠNG XE CƠ GIỚI\nNgày ban hành: 2024-11-15",
    "metadata": {
      "source": "Thông tư số 50_2024_TT-BGTVT",
      "effective_date": "1-1-2025",
      "url": "https://thuvienphapluat.vn/van-ban/Giao-thong-Van-tai/Thong-tu-50-2024-TT-BGTVT-Quy-chuan-ky-thuat-quoc-gia-ve-co-so-bao-hanh-bao-duong-xe-co-gioi-635820.aspx",
      "context": {}
    }
  },
  {
    "id": "50_2024_TT-BGTVT_chunk_2",
    "text": "Điều 1. Ban hành kèm theo Thông tư này:\n1. Quy chuẩn kỹ thuật quốc gia về cơ sở vật chất kỹ thuật và vị trí cơ sở đăng kiểm xe cơ giới, cơ sở kiểm định khí thải xe mô tô, xe gắn máy.\nMã số: QCVN 103:2024/BGTVT.",
    "metadata": {
      "source": "Thông tư số 50_2024_TT-BGTVT",
      "effective_date": "1-1-2025",
      "url": "https://thuvienphapluat.vn/van-ban/Giao-thong-Van-tai/Thong-tu-50-2024-TT-BGTVT-Quy-chuan-ky-thuat-quoc-gia-ve-co-so-bao-hanh-bao-duong-xe-co-gioi-635820.aspx",
      "context": {
        "khoan": "1",
        "dieu": "1"
      }
    }
  },
  {
    "id": "50_2024_TT-BGTVT_chunk_3",
    "text": "Điều 1. Ban hành kèm theo Thông tư này:\n2. Quy chuẩn kỹ thuật quốc gia về cơ sở bảo hành, bảo dưỡng xe cơ giới.\nMã số: QCVN 121:2025/BGTVT.",
    "metadata": {
      "source": "Thông tư số 50_2024_TT-BGTVT",
      "effective_date": "1-1-2025",
      "url": "https://thuvienphapluat.vn/van-ban/Giao-thong-Van-tai/Thong-tu-50-2024-TT-BGTVT-Quy-chuan-ky-thuat-quoc-gia-ve-co-so-bao-hanh-bao-duong-xe-co-gioi-635820.aspx",
      "context": {
        "khoan": "2",
        "dieu": "1"
      }
    }
  },
  {
    "id": "50_2024_TT-BGTVT_chunk_4",
    "text": "Điều 2.\n1. Thông tư này có hiệu lực thi hành kể từ ngày 01 tháng 01 năm 2025.",
    "metadata": {
      "source": "Thông tư số 50_2024_TT-BGTVT",
      "effective_date": "1-1-2025",
      "url": "https://thuvienphapluat.vn/van-ban/Giao-thong-Van-tai/Thong-tu-50-2024-TT-BGTVT-Quy-chuan-ky-thuat-quoc-gia-ve-co-so-bao-hanh-bao-duong-xe-co-gioi-635820.aspx",
      "context": {
        "khoan": "1",
        "dieu": "2"
      }
    }
  },
  {
    "id": "50_2024_TT-BGTVT_chunk_5",
    "text": "Điều 2.\n2. Bãi bỏ Thông tư số 30/2019/TT-BGTVT ngày 28 tháng 8 năm 2019 của Bộ trưởng Bộ Giao thông vận tải về việc ban hành Quy chuẩn kỹ thuật quốc gia về đơn vị đăng kiểm xe cơ giới QCVN 103:2019/BGTVT.",
    "metadata": {
      "source": "Thông tư số 50_2024_TT-BGTVT",
      "effective_date": "1-1-2025",
      "url": "https://thuvienphapluat.vn/van-ban/Giao-thong-Van-tai/Thong-tu-50-2024-TT-BGTVT-Quy-chuan-ky-thuat-quoc-gia-ve-co-so-bao-hanh-bao-duong-xe-co-gioi-635820.aspx",
      "context": {
        "khoan": "2",
        "dieu": "2"
      }
    }
  }
]